horovod/__init__.py
horovod/metadata.json
horovod/_keras/__init__.py
horovod/_keras/callbacks.py
horovod/_keras/elastic.py
horovod/common/__init__.py
horovod/common/basics.py
horovod/common/elastic.py
horovod/common/exceptions.py
horovod/common/process_sets.py
horovod/common/util.py
horovod/data/__init__.py
horovod/data/data_loader_base.py
horovod/keras/__init__.py
horovod/keras/callbacks.py
horovod/keras/elastic.py
horovod/mxnet/__init__.py
horovod/mxnet/compression.py
horovod/mxnet/functions.py
horovod/mxnet/mpi_ops.py
horovod/ray/__init__.py
horovod/ray/adapter.py
horovod/ray/driver_service.py
horovod/ray/elastic.py
horovod/ray/elastic_v2.py
horovod/ray/ray_logger.py
horovod/ray/runner.py
horovod/ray/strategy.py
horovod/ray/utils.py
horovod/ray/worker.py
horovod/runner/__init__.py
horovod/runner/gloo_run.py
horovod/runner/js_run.py
horovod/runner/launch.py
horovod/runner/mpi_run.py
horovod/runner/run_task.py
horovod/runner/task_fn.py
horovod/runner/common/__init__.py
horovod/runner/common/service/__init__.py
horovod/runner/common/service/compute_service.py
horovod/runner/common/service/driver_service.py
horovod/runner/common/service/task_service.py
horovod/runner/common/util/__init__.py
horovod/runner/common/util/codec.py
horovod/runner/common/util/config_parser.py
horovod/runner/common/util/env.py
horovod/runner/common/util/host_hash.py
horovod/runner/common/util/hosts.py
horovod/runner/common/util/network.py
horovod/runner/common/util/safe_shell_exec.py
horovod/runner/common/util/secret.py
horovod/runner/common/util/settings.py
horovod/runner/common/util/timeout.py
horovod/runner/common/util/tiny_shell_exec.py
horovod/runner/driver/__init__.py
horovod/runner/driver/driver_service.py
horovod/runner/elastic/__init__.py
horovod/runner/elastic/constants.py
horovod/runner/elastic/discovery.py
horovod/runner/elastic/driver.py
horovod/runner/elastic/registration.py
horovod/runner/elastic/rendezvous.py
horovod/runner/elastic/settings.py
intel_optimization_for_horovod-0.28.1.6.dist-info/LICENSE
intel_optimization_for_horovod-0.28.1.6.dist-info/METADATA
intel_optimization_for_horovod-0.28.1.6.dist-info/NOTICE
intel_optimization_for_horovod-0.28.1.6.dist-info/WHEEL
intel_optimization_for_horovod-0.28.1.6.dist-info/entry_points.txt
intel_optimization_for_horovod-0.28.1.6.dist-info/top_level.txt
intel_optimization_for_horovod-0.28.1.6.dist-info/RECORD
